getlinks/__init__.py
getlinks/getl.py
getlinks-0.1.4.dist-info/METADATA
getlinks-0.1.4.dist-info/WHEEL
getlinks-0.1.4.dist-info/entry_points.txt
getlinks-0.1.4.dist-info/RECORD
